termcaptor/__init__.py
termcaptor/cli.py
termcaptor/termcaptor.py
termcaptor-0.0.1.dist-info/LICENSE
termcaptor-0.0.1.dist-info/METADATA
termcaptor-0.0.1.dist-info/WHEEL
termcaptor-0.0.1.dist-info/entry_points.txt
termcaptor-0.0.1.dist-info/top_level.txt
termcaptor-0.0.1.dist-info/RECORD
