Metadata-Version: 2.1
Name: termcaptor
Version: 0.0.1
Summary: Record terminal sessions as SVG animations or GIF animations
Home-page: https://github.com/RexWzh/termcaptor
Author: Rex Wang
Author-email: 1073853456@qq.com
License: MIT license
Keywords: termcaptor
Classifier: Development Status :: 2 - Pre-Alpha
Classifier: Intended Audience :: Developers
Classifier: License :: OSI Approved :: MIT License
Classifier: Natural Language :: English
Classifier: Programming Language :: Python :: 2
Classifier: Programming Language :: Python :: 2.7
Classifier: Programming Language :: Python :: 3
Classifier: Programming Language :: Python :: 3.4
Classifier: Programming Language :: Python :: 3.5
Classifier: Programming Language :: Python :: 3.6
Classifier: Programming Language :: Python :: 3.7
License-File: LICENSE
Requires-Dist: Click (>=6.0)
